_flux/_core.abi3.so
_flux/_hostlist.abi3.so
_flux/_idset.abi3.so
_flux/_security.abi3.so
flux/.gitignore
flux/Makefile.am
flux/__init__.py
flux/compat36.py
flux/conf_builtin.py
flux/constants.py
flux/debugged.py
flux/eventlog.py
flux/future.py
flux/hostlist.py
flux/idset.py
flux/importer.py
flux/kvs.py
flux/memoized_property.py
flux/message.py
flux/modprobe.py
flux/progress.py
flux/queue.py
flux/rpc.py
flux/security.py
flux/util.py
flux/wrapper.py
flux/abc/__init__.py
flux/abc/journal.py
flux/cli/__init__.py
flux/cli/alloc.py
flux/cli/base.py
flux/cli/batch.py
flux/cli/bulksubmit.py
flux/cli/fortune.py
flux/cli/plugin.py
flux/cli/run.py
flux/cli/submit.py
flux/constraint/__init__.py
flux/constraint/parser.py
flux/core/__init__.py
flux/core/handle.py
flux/core/inner.py
flux/core/trampoline.py
flux/core/watchers.py
flux/job/JobID.py
flux/job/Jobspec.py
flux/job/__init__.py
flux/job/_wrapper.py
flux/job/directives.py
flux/job/event.py
flux/job/executor.py
flux/job/info.py
flux/job/journal.py
flux/job/kill.py
flux/job/kvs.py
flux/job/kvslookup.py
flux/job/list.py
flux/job/output.py
flux/job/stats.py
flux/job/submit.py
flux/job/timeleft.py
flux/job/wait.py
flux/job/watcher.py
flux/job/frobnicator/__init__.py
flux/job/frobnicator/frobnicator.py
flux/job/frobnicator/plugins/constraints.py
flux/job/frobnicator/plugins/defaults.py
flux/job/validator/__init__.py
flux/job/validator/validator.py
flux/job/validator/plugins/feasibility.py
flux/job/validator/plugins/jobspec.py
flux/job/validator/plugins/require-instance.py
flux/resource/ResourceSet.py
flux/resource/ResourceSetImplementation.py
flux/resource/Rlist.py
flux/resource/__init__.py
flux/resource/journal.py
flux/resource/list.py
flux/resource/status.py
flux/uri/__init__.py
flux/uri/uri.py
flux/uri/resolvers/jobid.py
flux/uri/resolvers/lsf.py
flux/uri/resolvers/pid.py
flux/uri/resolvers/slurm.py
flux/utils/README.md
flux/utils/dataclasses/3.6-notes.txt
flux/utils/dataclasses/LICENSE.txt
flux/utils/dataclasses/MANIFEST.in
flux_python-0.76.0.dist-info/licenses/LICENSE
flux_python-0.76.0.dist-info/licenses/NOTICE.LLNS
flux_python-0.76.0.dist-info/METADATA
flux_python-0.76.0.dist-info/WHEEL
flux_python-0.76.0.dist-info/top_level.txt
flux_python-0.76.0.dist-info/RECORD
