Metadata-Version: 2.1
Name: flux-python
Version: 0.76.0
Summary: Python bindings for the flux resource manager API
Home-page: https://github.com/flux-framework/flux-python
Keywords: flux,job manager,workload manager,orchestration,hpc
Classifier: Intended Audience :: Science/Research
Classifier: Intended Audience :: Developers
Classifier: License :: OSI Approved :: GNU Lesser General Public License v3 or later (LGPLv3+)
Classifier: Programming Language :: C++
Classifier: Programming Language :: Python
Classifier: Topic :: Software Development
Classifier: Topic :: Scientific/Engineering
Classifier: Operating System :: Unix
Classifier: Programming Language :: Python :: 3.6
Classifier: Programming Language :: Python :: 3.7
Classifier: Programming Language :: Python :: 3.8
Classifier: Programming Language :: Python :: 3.9
License-File: LICENSE
License-File: NOTICE.LLNS
Requires-Dist: cffi>=1.1
Requires-Dist: pyyaml
Provides-Extra: dev
Requires-Dist: pyyaml; extra == "dev"
Requires-Dist: jsonschema; extra == "dev"
Requires-Dist: docutils; extra == "dev"
Requires-Dist: black; extra == "dev"
Requires-Dist: IPython; extra == "dev"
